code_diff/__init__.py
code_diff/ast.py
code_diff/diff_utils.py
code_diff/sstubs.py
code_diff/utils.py
code_diff/gumtree/__init__.py
code_diff/gumtree/chawathe.py
code_diff/gumtree/editmap.py
code_diff/gumtree/isomap.py
code_diff/gumtree/ops.py
code_diff/gumtree/utils.py
code_diff-0.1.3.dist-info/LICENSE
code_diff-0.1.3.dist-info/METADATA
code_diff-0.1.3.dist-info/WHEEL
code_diff-0.1.3.dist-info/top_level.txt
code_diff-0.1.3.dist-info/RECORD
