Metadata-Version: 2.2
Name: code_diff
Version: 0.1.3
Summary: Fast AST based code differencing in Python
Home-page: https://github.com/cedricrupb/code_diff
Download-URL: https://github.com/cedricrupb/code_diff/archive/refs/tags/v0.1.3.tar.gz
Author: Cedric Richter
Author-email: Cedric Richter <cedricr.upb@gmail.com>
Maintainer-email: Cedric Richter <cedricr.upb@gmail.com>
Project-URL: Homepage, https://github.com/cedricrupb/code_diff
Project-URL: Bug Reports, https://github.com/cedricrupb/code_diff/issues
Project-URL: Source, https://github.com/cedricrupb/code_diff
Keywords: code,differencing,AST,CST,program,language processing
Classifier: Development Status :: 3 - Alpha
Classifier: Intended Audience :: Developers
Classifier: Topic :: Software Development :: Build Tools
Classifier: License :: OSI Approved :: MIT License
Classifier: Programming Language :: Python :: 3
Classifier: Programming Language :: Python :: 3.6
Classifier: Programming Language :: Python :: 3.7
Classifier: Programming Language :: Python :: 3.8
Classifier: Programming Language :: Python :: 3.9
Classifier: Programming Language :: Python :: 3.10
Classifier: Programming Language :: Python :: 3.11
Classifier: Programming Language :: Python :: 3.12
Classifier: Programming Language :: Python :: 3.13
Classifier: Programming Language :: Python :: 3 :: Only
Requires-Python: >=3.8
License-File: LICENSE
Requires-Dist: code_tokenize
Requires-Dist: apted
Dynamic: author
Dynamic: download-url
Dynamic: home-page
